{"model_name": "DecoderTransformer", "model_type": "PyTorch", "takes_target": false, "model_params": {"n_time_series": 30, "n_head": 8, "forecast_history": 90, "n_embd": 1, "num_layer": 5, "dropout": 0.1, "q_len": 1, "scale_att": false, "forecast_length": 30, "additional_params": {}}, "dataset_params": {"class": "default", "training_path": "../data/wind_train.csv", "validation_path": "../data/wind_train.csv", "test_path": "../data/wind_train.csv", "batch_size": 64, "forecast_history": 90, "forecast_length": 30, "train_end": 7669, "valid_start": 7670, "valid_end": 9861, "target_col": ["Austria"], "relevant_cols": ["Austria", "Belgium", "Bulgaria", "Switzerland", "Czechia", "Germany", "Denmark", "Estonia", "Spain", "Finland", "France", "Greece", "Croatia", "Hungary", "Ireland", "Italy", "Lithuania", "Luxembourg", "Latvia", "Netherlands", "Norway", "Poland", "Portugal", "Romania", "Slovenia", "Slovakia", "Sweden", "United Kingdom", "month", "weekday"], "scaler": "StandardScaler", "interpolate": false, "sort_column": "time"}, "training_params": {"criterion": "DilateLoss", "optimizer": "Adam", "optim_params": {}, "lr": 0.001, "epochs": 2, "batch_size": 64}, "early_stopping": {"patience": 3}, "GCS": false, "sweep": false, "wandb": false, "forward_params": {}, "metrics": ["RMSE", "MAPE"], "inference_params": {"datetime_start": "2010-01-01", "hours_to_forecast": 2000, "test_csv_path": "../data/wind_train.csv", "decoder_params": {"decoder_function": "simple_decode", "unsqueeze_dim": 1}, "dataset_params": {"file_path": "../data/wind_train.csv", "forecast_history": 90, "forecast_length": 30, "relevant_cols": ["Austria", "Belgium", "Bulgaria", "Switzerland", "Czechia", "Germany", "Denmark", "Estonia", "Spain", "Finland", "France", "Greece", "Croatia", "Hungary", "Ireland", "Italy", "Lithuania", "Luxembourg", "Latvia", "Netherlands", "Norway", "Poland", "Portugal", "Romania", "Slovenia", "Slovakia", "Sweden", "United Kingdom", "month", "weekday"], "target_col": ["Austria"], "scaling": "StandardScaler", "interpolate_param": false}}, "meta_data": false, "run": [{"epoch": 0, "train_loss": "6.497596100225287", "validation_loss": "1922.8517450094223"}, {"epoch": 1, "train_loss": "4.563948233248824", "validation_loss": "1868.363129734993"}]}